{
    "pontos": [
        {
            "titulo": "DEFUMAÇÃO",
            "descricao": "Nesta casa tem quatro cantos\nEm cada canto tem uma flor\nNesta casa não entra maldade\nNesta casa só entra o amor.\n----------------------------------------------------------\nEu defumo com as ervas da Jurema\nEu defumo com Arruda e Guiné\nAlecrim Benjoim e Alfazema\nVem defumar estes filhos de fé.\n----------------------------------------------------------\nOlha firma o pensamento\nNa hora de defumar\nEu defumo esta canjira\nNa fé de Pai Oxalá\nDefuma vou defumar\nCom a força de Pai Oxalá.\n----------------------------------------------------------\nDefumador de caboclo\nQue cheira guiné\nOlha vamos defumar\nEstes filhos de fé\nDefuma eu, babá\nDefuma eu babá.\n----------------------------------------------------------\n"
        },
        {
            "titulo": "EXÚ",
            "descricao": "Soltaram um pombo lá nas matas\nAi na pedreira não chegou\nFoi parar na encruzilhada\nSeu Tranca Ruas quem mandou.\n----------------------------------------------------------\nTava dormindo\nQuando o malvado chegou\nCom a sua capa preta\nDizendo que era Doutor\nMais ele era Exu\nDizendo que era Doutor. (bis)\nExu no terreiro é Rei\nNa encruza ele é doutor\nExu venceu demanda\nExu é curador.\n----------------------------------------------------------\nÉ noite escura, iaia\nAcende a vela\n7 coroas é o bamba da favela\nÉs malandrinho não precisa trabalhar\n7 coroas vai por tudo em seu lugar.\n----------------------------------------------------------\nEu vi homem sentado\nDebaixo da amendoeira\nEra osso só\nEra João Caveira.\n----------------------------------------------------------\nExú Tiriririri é o rei da encruzilhada!\nToma conta e presta conta\nNo romper da madrugada.\n----------------------------------------------------------\nTiriri ééé... meu amigo leal (bis)\nToma conta do seu terreiro\nToma conta do seu quintal.\n----------------------------------------------------------\nPortão de ferro\nCadeado de madeira\no portão do cemitério quem mora lá? É Exú Caveira.\n----------------------------------------------------------\nSeu Zé Pelintra quando vier lá de Alagoas\nToma cuidado com o balanço da canoa\nOi Zé faça tudo que quiser\nSó não maltrate o coração desta mulher.\n----------------------------------------------------------\nExu da meia noite\nExu da encruzilhada\nSalve o povo da quimbanda\nSem Exu não se faz nada.\n----------------------------------------------------------\nSe ele é Exu\nAgora que eu quero ver\nÉ nos pés de Exu Veludo\nTodo Exu tem que descer.\n----------------------------------------------------------\nÉ de manhã, quando eu desço a ladeira (bis)\nA nega pensa que eu vou é trabalhar\nMas eu coloco, meu baralho no bolso\nCachecol no pescoço\nE vou pra praça Mauá (bis)\nTrabalhar, trabalhar pra quê\nSe eu trabalhar\nEu vou morrer.\n----------------------------------------------------------\nOlha pisa no toco\nPisa no galho\nO galho balança Exu não cai\nO gonga ê ê Exu\nOlha pisa no toco de galho só.\n----------------------------------------------------------\n"
        },
        {
            "titulo": "POMBO GIRA",
            "descricao": "Ganhei uma barraca dela\nFoi a cigana quem me deu\nO que é meu é da cigana\nO que é dela não é meu.\n----------------------------------------------------------\nPombo Gira é mulher de 7 maridos\nNão mexe com ela\nQue ela é um perigo.\n----------------------------------------------------------\nArreda homem, que ai vem mulher\nEla é a Pombo Gira rainha do cabaré\nSeu Tranca Rua vem na frente\nMostrando quem ela é\nEla é a Pombo Gira rainha do cabaré.\n----------------------------------------------------------\nVinha caminhando a pé\nPara ver se encontrava\nMinha cigana de fé\nEla parou e leu minha mão\nE disse toda a verdade\nEu só queria saber\nAonde mora Pombo Gira Cigana.\n----------------------------------------------------------\n"
        },
        {
            "titulo": "PRETOS VELHOS",
            "descricao": "Pai André tem muita cangira\nMas povo de Umbanda\nMandou lhe chamar (bis)\nQuero ver Pain André descer\nSeu corpo balancear (bis)\n----------------------------------------------------------\nPai Antônio e Pai Benedito\nSão dois irmãos\nPai Antônio trabalha na mesa\nPai Benedito trabalha no chão.\n----------------------------------------------------------\nSe a cana é dura\nÉ dura de quebrar\nCoração que não bambeia\nHoje tem que bambear.\n----------------------------------------------------------\nMãe Maria, Mãe Cambinda\nLavadeira de sinhá\nLava as chagas de seus filhos\nJoga nas ondas do mar\nEla já girou, ela vai girar\nE o mau do dos filhos\nMãe Cambinda vai levar.\n----------------------------------------------------------\nVovô não quer\nCasca de Cocô no terreiro (bis)\nQue é pra não lembrar\nDos tempos do cativeiro.\n----------------------------------------------------------\nLá no céu\nVem descendo\nUma coroa\nEsta coroa é da Virgem da Glória\nVamos apanhar ela com jeito\nMeus irmãos\nEsta coroa é de Nossa Senhora.\n----------------------------------------------------------\n"
        },
        {
            "titulo": "NANÃ",
            "descricao": "Flores roxas no terreiro\nVamos todos saravá\nÉ Nanã que vem primeiro\nNo barco que vem do mar\nÊ ê ê ê é Nanã que vem primeiro\nÊ ê ê a no barco que vem do mar\nNanã Buruquê protege os filhos deste gongá\nNanã Buruquê é Mãe, Mãe de todos os Orixás\nÊ ê ê ê é Nanã que vem primeiro\nÊ ê ê a no barco que vem do mar\nA água nasce na fonte, da fonte a cachoeira\nVem na linha de Nanã e na força da pedreira.\n----------------------------------------------------------\nNascente pequenina\nAonde nasceu Nanã (bis)\nAi minha avó\nVovozina inanaê.\n----------------------------------------------------------\nUma velha muito velha\nQue veio de urucaia\nEla chama Nanã Buruquê\nEla chama Nanã Buruquê.\nCom a força de Pai Oxalá.\n----------------------------------------------------------\n"
        },
        {
            "titulo": "IANSÃ",
            "descricao": "Ô imbera\nImberá é Iansã\nRainha de imberá\nÉ Iansã.\n----------------------------------------------------------\nIansã\nTem leque de pena\nPra abanar dia de calor\nIansã mora na pedreira\nEu quero ver meu pai Xangô.\nVovozina inanaê.\n----------------------------------------------------------\nUOlha isá cutala\nNo arê, rê\nÉ, rê é, no a rê rê\nÉ rê ela tem dendê\nOlha isacutalá no arê arê\nÊêê ela tem dendê êêê..\n----------------------------------------------------------\n"
        },
        {
            "titulo": "OBALUAIÊ",
            "descricao": "Meu Pai Oxalá\nSeu rei venha me valer\nE o velho omulu\nA tô tô Obaluaiê a tô tô Obaluaiê êê\nA tô tô babá\nA tô tô Obaluaiê êê a tô tô é Orixá.\n----------------------------------------------------------\nAndei, andei, meu pai\nNão sei porque\nA minha sina papai é padecer\nBateu na porta meu pai\nFui atender\nÉ Obaluaiê que vem nos socorrer.\n----------------------------------------------------------\n"
        },
        {
            "titulo": "OGUM",
            "descricao": "Estava lá na beira da praia\nQuando eu vi sete ondas rolar\nOi abre as portas ô gente\nQue ai vem Ogum\nEm seu cavalo marinho\nEle vem saravá.\n----------------------------------------------------------\nSe meu Pai é Ogum\nVencedor de demanda\nEle vem de aruanda\nPra salvar filho de umbanda\nOgum, Ogum Iara (bis)\nSalve os campos de batalha\nSalve as sereias do mar\nOgum, Ogum Iara.\n----------------------------------------------------------\nOgum já jurou Bandeira\nNa porta do humaitá\nOgum já venceu demanda\nVamos todos saravá.\n----------------------------------------------------------\nBandeira linda de Ogum\nEstá içada lá no humaitá\nE representa general de umbanda\nOgum vence demanda\nEm qualquer lugar.\n----------------------------------------------------------\nSeu Ogum beira mar\nO que trouxe do mar (bis)\nQuando ele vem\nBeirando a areia\nNa mão direita ele traz\nUma guia da Mamãe Sereia."
        },
        {
            "titulo": "OXALÁ",
            "descricao": "Oxalá meu pai\nTem pena de nós, tem dó\nA volta do mundo é grande\nSeus poderes são maior.\n----------------------------------------------------------\n"
        },
        {
            "titulo": "OXOSSI",
            "descricao": "Meu Pai Oxóssi\nCavaleiro da lua\nQue veio ao mundo para clarear\nSó queria Ter agora\nMeu pai Oxóssi\nNeste casuá.\n----------------------------------------------------------\nQuem manda nas matas é Oxóssi\nOxóssi é caçador (bis)\nE na aruanda auê\nÉ na aruanda auê\nAh! O rei Oxóssi de umbanda\nÉ na aruanda auê\n----------------------------------------------------------\n"
        },
        {
            "titulo": "OXUM",
            "descricao": "Eu vi mamãe Oxum na cachoeira\nSentada na beira do rio (bis)\nColhendo lírio, lírio ê\nColhendo lírio, lírio, á\nColhendo lírio\nPra enfeitar nosso congá.\n----------------------------------------------------------\n"
        },
        {
            "titulo": "XANGÔ",
            "descricao": "Xangô é rei\nÉ rei Nagô\nOi bate palma\nPra coroa de Xangô\nOi bate palma\nPra coroa de Xangô.\n----------------------------------------------------------\nSua machadinha de ouro\nÉ de ouro e de ouro (bis)\nMachadinha que corta mironga\nÉ machadinha de Xangô (bis)\n----------------------------------------------------------\nSentado na pedreira de Xangô\nEu fiz meu juramento até o fim (bis)\nSe um dia eu quebrar,\nA fé no meu Senhor,\nQue role esta pedreira sobre mim.\n----------------------------------------------------------\nXangô é curisco\nMora na pedra furada\nEle deita meia noite\nLevanta de madrugada.\n----------------------------------------------------------\nKaô, kaô\nO de lê, o de lá\nKaô cabecile\nO de lê, o de lá.\n----------------------------------------------------------\n"
        },
        {
            "titulo": "YEMANJÁ",
            "descricao": "Eu vou jogar, vou jogar flores no mar\nEu vou jogar\nUma promessa que eu fiz\nPara a deusa do mar\nO meu pedido atendeu\nEu recebi, vou pagar.\n----------------------------------------------------------\n"
        },
        {
            "titulo": "OXUMARÊ",
            "descricao": "OxuMarê\nLá na angola é angorô (bis)\nOxuMarê\nLá na angola é angorô\nOxuMarê.\n----------------------------------------------------------\nOxum oi que Marê,\nOi que Marê Oxum (bis)\nOxum oi que Marê,\nMarê, Marê Oxum."
        }
    ]
}